gwvet/__init__.py
gwvet/__main__.py
gwvet/_version.py
gwvet/core.py
gwvet/etg.py
gwvet/hug.py
gwvet/segments.py
gwvet/tabs.py
gwvet/triggers.py
gwvet/vdf.py
gwvet/cli/__init__.py
gwvet/cli/flag.py
gwvet/metric/__init__.py
gwvet/metric/core.py
gwvet/metric/metrics.py
gwvet/metric/registry.py
gwvet-1.0.4.dist-info/LICENSE
gwvet-1.0.4.dist-info/METADATA
gwvet-1.0.4.dist-info/WHEEL
gwvet-1.0.4.dist-info/entry_points.txt
gwvet-1.0.4.dist-info/top_level.txt
gwvet-1.0.4.dist-info/RECORD
