Metadata-Version: 2.1
Name: gwvet
Version: 1.0.4
Summary: An extension to the python toolbox GWSumm, used by the LIGO Scientific Collaboration to review data-quality vetoes
Home-page: https://github.com/gwpy/vet
Author: Alex Urban, Duncan Macleod
Author-email: alexander.urban@ligo.org
License: GPL-3.0-or-later
Project-URL: Bug Tracker, https://github.com/gwpy/vet/issues
Project-URL: Discussion Forum, https://gwdetchar.slack.com
Project-URL: Source Code, https://github.com/gwpy/vet
Keywords: physics,astronomy,gravitational-waves,ligo
Classifier: Development Status :: 5 - Production/Stable
Classifier: Intended Audience :: Developers
Classifier: Intended Audience :: Science/Research
Classifier: License :: OSI Approved :: GNU General Public License v3 or later (GPLv3+)
Classifier: Natural Language :: English
Classifier: Operating System :: OS Independent
Classifier: Programming Language :: Python
Classifier: Programming Language :: Python :: 3
Classifier: Programming Language :: Python :: 3.6
Classifier: Programming Language :: Python :: 3.7
Classifier: Programming Language :: Python :: 3.8
Classifier: Programming Language :: Python :: 3.9
Classifier: Topic :: Scientific/Engineering
Classifier: Topic :: Scientific/Engineering :: Astronomy
Classifier: Topic :: Scientific/Engineering :: Physics
Requires-Python: >=3.6
License-File: LICENSE
Requires-Dist: astropy >=3.0.0
Requires-Dist: decorator
Requires-Dist: dqsegdb
Requires-Dist: gwdetchar >=2.0.0
Requires-Dist: gwpy >=2.0.0
Requires-Dist: gwsumm >=2.0.0
Requires-Dist: gwtrigfind
Requires-Dist: lscsoft-glue >=1.60.0
Requires-Dist: MarkupPy
Requires-Dist: matplotlib >=3.1
Requires-Dist: numpy >=1.16
Requires-Dist: scipy
Provides-Extra: doc
Requires-Dist: sphinx ; extra == 'doc'
Requires-Dist: numpydoc ; extra == 'doc'
Requires-Dist: sphinx-rtd-theme ; extra == 'doc'
Requires-Dist: sphinxcontrib-epydoc ; extra == 'doc'
